README.md
setup.cfg
setup.py
seymens_package/Binomialdistribution.py
seymens_package/Gaussiandistribution.py
seymens_package/Generaldistribution.py
seymens_package/__init__.py
seymens_package.egg-info/PKG-INFO
seymens_package.egg-info/SOURCES.txt
seymens_package.egg-info/dependency_links.txt
seymens_package.egg-info/not-zip-safe
seymens_package.egg-info/top_level.txt